maritimeviz/__init__.py
maritimeviz/ais_db.py
maritimeviz/auth.py
maritimeviz/cli.py
maritimeviz/constants.py
maritimeviz/gfw_api.py
maritimeviz/maritimeviz.py
maritimeviz/viz.py
maritimeviz/utils/__init__.py
maritimeviz/utils/ais_db_utils.py
maritimeviz/utils/logging_utils.py
maritimeviz/utils/viz_utils.py
maritimeviz-0.1.0.dist-info/licenses/AUTHORS.rst
maritimeviz-0.1.0.dist-info/licenses/LICENSE
maritimeviz-0.1.0.dist-info/METADATA
maritimeviz-0.1.0.dist-info/WHEEL
maritimeviz-0.1.0.dist-info/entry_points.txt
maritimeviz-0.1.0.dist-info/top_level.txt
maritimeviz-0.1.0.dist-info/RECORD
