Metadata-Version: 2.4
Name: maritimeviz
Version: 0.1.0
Summary: A Python package designed to analyze and visualize Automatic Identification System (AIS) data, enabling easy exploration of maritime vessel movements through data extraction, cleaning, and analysis. Utilize powerful libraries like NumPy and Pandas for efficient data manipulation, and leverage the interactive mapping capabilities of Leafmap for insightful visualizations of vessel trajectories and other key maritime information.
Author-email: "Thalia Valle, Marcelo Amorin, Henrique Baggio" <thaliasaxo@gmail.com>
Maintainer-email: "Thalia Valle, Marcelo Amorin, Henrique Baggio" <thaliasaxo@gmail.com>
License-Expression: MIT
Project-URL: bugs, https://github.com/Thaliavch/maritimeviz/issues
Project-URL: changelog, https://github.com/Thaliavch/maritimeviz/blob/master/changelog.md
Project-URL: homepage, https://github.com/Thaliavch/maritimeviz
Requires-Python: >=3.11
License-File: LICENSE
License-File: AUTHORS.rst
Requires-Dist: typer>=0.15.0
Requires-Dist: libais>=0.17
Requires-Dist: duckdb>=0.7.1
Requires-Dist: pandas>=1.5.0
Requires-Dist: geopandas>=0.13.0
Requires-Dist: shapely>=1.8.0
Requires-Dist: python-dotenv
Requires-Dist: leafmap>=0.20.0
Requires-Dist: folium>=0.12.1
Requires-Dist: branca>=0.6.0
Requires-Dist: ipyleaflet>=0.19.0
Requires-Dist: ipython>=7.34.0
Requires-Dist: requests>=2.28.0
Requires-Dist: cachetools>=5.0.0
Requires-Dist: matplotlib>=3.5.0
Requires-Dist: geopy
Provides-Extra: dev
Requires-Dist: coverage; extra == "dev"
Requires-Dist: mypy; extra == "dev"
Requires-Dist: pytest; extra == "dev"
Requires-Dist: ruff; extra == "dev"
Provides-Extra: parquet
Requires-Dist: pyarrow; extra == "parquet"
Dynamic: license-file
